ktblame/__init__.py
ktblame/builtin/__init__.py
ktblame/builtin/extractors.py
ktblame/builtin/streamlit.py
ktblame-0.0.2.dist-info/LICENSE
ktblame-0.0.2.dist-info/METADATA
ktblame-0.0.2.dist-info/WHEEL
ktblame-0.0.2.dist-info/top_level.txt
ktblame-0.0.2.dist-info/RECORD
